{"cardData": {"Banish from Edoras": {"Name": "Banish from Edoras", "Color": "W", "Rarity": "common", "# GIH": 59935, "OH WR": "51.0%", "GIH WR": "56.6%", "ATA": "7.73", "ALSA": "5.22", "IWD": "1.7pp", "zScoreGIH": 0.073, "zScoreOH": -0.41, "zScoreIWD": -0.29}, "The Battle of Bywater": {"Name": "The Battle of Bywater", "Color": "W", "Rarity": "rare", "# GIH": 9338, "OH WR": "54.2%", "GIH WR": "57.8%", "ATA": "3.28", "ALSA": "2.87", "IWD": "3.52pp", "zScoreGIH": 0.308, "zScoreOH": 0.086, "zScoreIWD": 0.126}, "Bill the Pony": {"Name": "Bill the Pony", "Color": "W", "Rarity": "uncommon", "# GIH": 37439, "OH WR": "55.7%", "GIH WR": "58.1%", "ATA": "4.37", "ALSA": "3.52", "IWD": "4.44pp", "zScoreGIH": 0.367, "zScoreOH": 0.32, "zScoreIWD": 0.339}, "Boromir, Warden of the Tower": {"Name": "Boromir, Warden of the Tower", "Color": "W", "Rarity": "rare", "# GIH": 13390, "OH WR": "60.1%", "GIH WR": "59.1%", "ATA": "2.1", "ALSA": "1.97", "IWD": "6.56pp", "zScoreGIH": 0.564, "zScoreOH": 1.005, "zScoreIWD": 0.83}, "Dawn of a New Age": {"Name": "Dawn of a New Age", "Color": "W", "Rarity": "mythic", "# GIH": 5357, "OH WR": "53.4%", "GIH WR": "54.8%", "ATA": "2.18", "ALSA": "2.08", "IWD": "1.43pp", "zScoreGIH": -0.28, "zScoreOH": -0.03, "zScoreIWD": -0.35}, "D\u00fanedain Blade": {"Name": "D\u00fanedain Blade", "Color": "W", "Rarity": "common", "# GIH": 22300, "OH WR": "52.5%", "GIH WR": "52.9%", "ATA": "11.15", "ALSA": "7.72", "IWD": "-2.61pp", "zScoreGIH": -0.65, "zScoreOH": -0.17, "zScoreIWD": -1.29}, "Eagles of the North": {"Name": "Eagles of the North", "Color": "W", "Rarity": "common", "# GIH": 88385, "OH WR": "53.4%", "GIH WR": "56.2%", "ATA": "7.42", "ALSA": "5.18", "IWD": "0.92pp", "zScoreGIH": -0.0, "zScoreOH": -0.03, "zScoreIWD": -0.47}, "Eastfarthing Farmer": {"Name": "Eastfarthing Farmer", "Color": "W", "Rarity": "common", "# GIH": 50985, "OH WR": "54.8%", "GIH WR": "57.4%", "ATA": "8.94", "ALSA": "6.15", "IWD": "3.16pp", "zScoreGIH": 0.23, "zScoreOH": 0.179, "zScoreIWD": 0.043}, "East-Mark Cavalier": {"Name": "East-Mark Cavalier", "Color": "W", "Rarity": "common", "# GIH": 63559, "OH WR": "55.2%", "GIH WR": "54.5%", "ATA": "8.86", "ALSA": "6.16", "IWD": "0.16pp", "zScoreGIH": -0.33, "zScoreOH": 0.242, "zScoreIWD": -0.65}, "\u00c9owyn, Lady of Rohan": {"Name": "\u00c9owyn, Lady of Rohan", "Color": "W", "Rarity": "uncommon", "# GIH": 32400, "OH WR": "55.8%", "GIH WR": "56.6%", "ATA": "3.9", "ALSA": "3.11", "IWD": "2.85pp", "zScoreGIH": 0.073, "zScoreOH": 0.335, "zScoreIWD": -0.02}, "Errand-Rider of Gondor": {"Name": "Errand-Rider of Gondor", "Color": "W", "Rarity": "common", "# GIH": 115466, "OH WR": "55.9%", "GIH WR": "58.2%", "ATA": "5.21", "ALSA": "3.98", "IWD": "3.0pp", "zScoreGIH": 0.387, "zScoreOH": 0.351, "zScoreIWD": 0.006}, "Escape from Orthanc": {"Name": "Escape from Orthanc", "Color": "W", "Rarity": "common", "# GIH": 22021, "OH WR": "53.7%", "GIH WR": "55.9%", "ATA": "11.33", "ALSA": "8.02", "IWD": "0.34pp", "zScoreGIH": -0.06, "zScoreOH": 0.008, "zScoreIWD": -0.6}, "Esquire of the King": {"Name": "Esquire of the King", "Color": "W", "Rarity": "common", "# GIH": 41661, "OH WR": "54.4%", "GIH WR": "53.4%", "ATA": "10.17", "ALSA": "7.06", "IWD": "-0.81pp", "zScoreGIH": -0.55, "zScoreOH": 0.117, "zScoreIWD": -0.87}, "Faramir, Field Commander": {"Name": "Faramir, Field Commander", "Color": "W", "Rarity": "uncommon", "# GIH": 32834, "OH WR": "52.0%", "GIH WR": "55.3%", "ATA": "3.24", "ALSA": "2.72", "IWD": "1.58pp", "zScoreGIH": -0.18, "zScoreOH": -0.25, "zScoreIWD": -0.32}, "Flowering of the White Tree": {"Name": "Flowering of the White Tree", "Color": "W", "Rarity": "rare", "# GIH": 13514, "OH WR": "59.3%", "GIH WR": "58.7%", "ATA": "1.85", "ALSA": "1.86", "IWD": "6.33pp", "zScoreGIH": 0.485, "zScoreOH": 0.88, "zScoreIWD": 0.777}, "Fog on the Barrow-Downs": {"Name": "Fog on the Barrow-Downs", "Color": "W", "Rarity": "common", "# GIH": 39722, "OH WR": "49.0%", "GIH WR": "54.3%", "ATA": "8.29", "ALSA": "5.52", "IWD": "-0.76pp", "zScoreGIH": -0.37, "zScoreOH": -0.72, "zScoreIWD": -0.86}, "Forge Anew": {"Name": "Forge Anew", "Color": "W", "Rarity": "rare", "# GIH": 125, "OH WR": "38.8%", "GIH WR": "39.5%", "ATA": "9.2", "ALSA": "5.96", "IWD": "-6.73pp", "zScoreGIH": -3.28, "zScoreOH": -2.31, "zScoreIWD": -2.24}, "Frodo, Sauron's Bane": {"Name": "Frodo, Sauron's Bane", "Color": "W", "Rarity": "rare", "# GIH": 11607, "OH WR": "62.9%", "GIH WR": "56.6%", "ATA": "2.63", "ALSA": "2.43", "IWD": "5.93pp", "zScoreGIH": 0.073, "zScoreOH": 1.441, "zScoreIWD": 0.684}, "Gandalf the White": {"Name": "Gandalf the White", "Color": "W", "Rarity": "mythic", "# GIH": 4977, "OH WR": "51.9%", "GIH WR": "54.4%", "ATA": "1.71", "ALSA": "1.73", "IWD": "1.08pp", "zScoreGIH": -0.35, "zScoreOH": -0.27, "zScoreIWD": -0.43}, "Hobbit's Sting": {"Name": "Hobbit's Sting", "Color": "W", "Rarity": "common", "# GIH": 72593, "OH WR": "53.1%", "GIH WR": "56.4%", "ATA": "7.19", "ALSA": "5.11", "IWD": "1.33pp", "zScoreGIH": 0.033, "zScoreOH": -0.08, "zScoreIWD": -0.38}, "Landroval, Horizon Witness": {"Name": "Landroval, Horizon Witness", "Color": "W", "Rarity": "uncommon", "# GIH": 24849, "OH WR": "53.1%", "GIH WR": "56.3%", "ATA": "5.23", "ALSA": "3.92", "IWD": "2.52pp", "zScoreGIH": 0.014, "zScoreOH": -0.08, "zScoreIWD": -0.1}, "Lost to Legend": {"Name": "Lost to Legend", "Color": "W", "Rarity": "uncommon", "# GIH": 25387, "OH WR": "52.8%", "GIH WR": "56.7%", "ATA": "7.69", "ALSA": "5.64", "IWD": "1.04pp", "zScoreGIH": 0.092, "zScoreOH": -0.13, "zScoreIWD": -0.44}, "Nimble Hobbit": {"Name": "Nimble Hobbit", "Color": "W", "Rarity": "common", "# GIH": 17859, "OH WR": "51.0%", "GIH WR": "52.5%", "ATA": "11.4", "ALSA": "7.87", "IWD": "-0.43pp", "zScoreGIH": -0.73, "zScoreOH": -0.41, "zScoreIWD": -0.78}, "Now for Wrath, Now for Ruin!": {"Name": "Now for Wrath, Now for Ruin!", "Color": "W", "Rarity": "common", "# GIH": 15394, "OH WR": "49.9%", "GIH WR": "53.1%", "ATA": "11.31", "ALSA": "7.64", "IWD": "-1.58pp", "zScoreGIH": -0.61, "zScoreOH": -0.58, "zScoreIWD": -1.05}, "Protector of Gondor": {"Name": "Protector of Gondor", "Color": "W", "Rarity": "common", "# GIH": 92747, "OH WR": "56.2%", "GIH WR": "57.9%", "ATA": "7.3", "ALSA": "5.32", "IWD": "2.42pp", "zScoreGIH": 0.328, "zScoreOH": 0.398, "zScoreIWD": -0.12}, "Reprieve": {"Name": "Reprieve", "Color": "W", "Rarity": "uncommon", "# GIH": 35710, "OH WR": "58.0%", "GIH WR": "57.8%", "ATA": "5.46", "ALSA": "4.23", "IWD": "3.76pp", "zScoreGIH": 0.308, "zScoreOH": 0.678, "zScoreIWD": 0.182}, "Rosie Cotton of South Lane": {"Name": "Rosie Cotton of South Lane", "Color": "W", "Rarity": "uncommon", "# GIH": 36489, "OH WR": "55.9%", "GIH WR": "58.4%", "ATA": "3.32", "ALSA": "2.82", "IWD": "4.27pp", "zScoreGIH": 0.426, "zScoreOH": 0.351, "zScoreIWD": 0.3}, "Samwise the Stouthearted": {"Name": "Samwise the Stouthearted", "Color": "W", "Rarity": "uncommon", "# GIH": 41963, "OH WR": "56.0%", "GIH WR": "57.9%", "ATA": "3.09", "ALSA": "2.65", "IWD": "3.92pp", "zScoreGIH": 0.328, "zScoreOH": 0.366, "zScoreIWD": 0.219}, "Second Breakfast": {"Name": "Second Breakfast", "Color": "W", "Rarity": "common", "# GIH": 9971, "OH WR": "49.4%", "GIH WR": "53.1%", "ATA": "11.78", "ALSA": "8.07", "IWD": "-0.31pp", "zScoreGIH": -0.61, "zScoreOH": -0.66, "zScoreIWD": -0.75}, "Shire Shirriff": {"Name": "Shire Shirriff", "Color": "W", "Rarity": "uncommon", "# GIH": 35023, "OH WR": "54.4%", "GIH WR": "57.3%", "ATA": "4.35", "ALSA": "3.46", "IWD": "1.94pp", "zScoreGIH": 0.21, "zScoreOH": 0.117, "zScoreIWD": -0.23}, "Slip On the Ring": {"Name": "Slip On the Ring", "Color": "W", "Rarity": "common", "# GIH": 27103, "OH WR": "50.8%", "GIH WR": "54.4%", "ATA": "10.56", "ALSA": "7.19", "IWD": "0.52pp", "zScoreGIH": -0.35, "zScoreOH": -0.44, "zScoreIWD": -0.56}, "Soldier of the Grey Host": {"Name": "Soldier of the Grey Host", "Color": "W", "Rarity": "common", "# GIH": 13872, "OH WR": "51.2%", "GIH WR": "54.1%", "ATA": "11.21", "ALSA": "7.52", "IWD": "1.26pp", "zScoreGIH": -0.41, "zScoreOH": -0.38, "zScoreIWD": -0.39}, "Stalwarts of Osgiliath": {"Name": "Stalwarts of Osgiliath", "Color": "W", "Rarity": "common", "# GIH": 41831, "OH WR": "52.7%", "GIH WR": "57.1%", "ATA": "9.69", "ALSA": "6.62", "IWD": "2.36pp", "zScoreGIH": 0.171, "zScoreOH": -0.14, "zScoreIWD": -0.14}, "Tale of Tin\u00faviel": {"Name": "Tale of Tin\u00faviel", "Color": "W", "Rarity": "uncommon", "# GIH": 11649, "OH WR": "48.7%", "GIH WR": "53.1%", "ATA": "7.97", "ALSA": "5.44", "IWD": "0.03pp", "zScoreGIH": -0.61, "zScoreOH": -0.77, "zScoreIWD": -0.68}, "Took Reaper": {"Name": "Took Reaper", "Color": "W", "Rarity": "common", "# GIH": 67698, "OH WR": "53.1%", "GIH WR": "54.1%", "ATA": "8.76", "ALSA": "6.11", "IWD": "-0.43pp", "zScoreGIH": -0.41, "zScoreOH": -0.08, "zScoreIWD": -0.78}, "War of the Last Alliance": {"Name": "War of the Last Alliance", "Color": "W", "Rarity": "rare", "# GIH": 8938, "OH WR": "58.9%", "GIH WR": "60.7%", "ATA": "3.74", "ALSA": "3.16", "IWD": "6.7pp", "zScoreGIH": 0.878, "zScoreOH": 0.818, "zScoreIWD": 0.862}, "Westfold Rider": {"Name": "Westfold Rider", "Color": "W", "Rarity": "common", "# GIH": 78025, "OH WR": "55.1%", "GIH WR": "54.8%", "ATA": "7.92", "ALSA": "5.58", "IWD": "0.15pp", "zScoreGIH": -0.28, "zScoreOH": 0.226, "zScoreIWD": -0.65}, "You Cannot Pass!": {"Name": "You Cannot Pass!", "Color": "W", "Rarity": "uncommon", "# GIH": 8267, "OH WR": "49.6%", "GIH WR": "53.0%", "ATA": "9.76", "ALSA": "6.49", "IWD": "0.01pp", "zScoreGIH": -0.63, "zScoreOH": -0.63, "zScoreIWD": -0.68}, "Arwen's Gift": {"Name": "Arwen's Gift", "Color": "U", "Rarity": "common", "# GIH": 85405, "OH WR": "52.2%", "GIH WR": "58.4%", "ATA": "8.3", "ALSA": "5.89", "IWD": "4.02pp", "zScoreGIH": 0.426, "zScoreOH": -0.22, "zScoreIWD": 0.242}, "The Bath Song": {"Name": "The Bath Song", "Color": "U", "Rarity": "uncommon", "# GIH": 61242, "OH WR": "57.0%", "GIH WR": "61.6%", "ATA": "4.28", "ALSA": "3.77", "IWD": "7.69pp", "zScoreGIH": 1.055, "zScoreOH": 0.522, "zScoreIWD": 1.092}, "Bewitching Leechcraft": {"Name": "Bewitching Leechcraft", "Color": "U", "Rarity": "common", "# GIH": 25908, "OH WR": "48.5%", "GIH WR": "55.3%", "ATA": "10.54", "ALSA": "7.05", "IWD": "3.17pp", "zScoreGIH": -0.18, "zScoreOH": -0.8, "zScoreIWD": 0.045}, "Bill Ferny, Bree Swindler": {"Name": "Bill Ferny, Bree Swindler", "Color": "U", "Rarity": "uncommon", "# GIH": 16701, "OH WR": "51.4%", "GIH WR": "53.1%", "ATA": "9.15", "ALSA": "6.21", "IWD": "1.61pp", "zScoreGIH": -0.61, "zScoreOH": -0.34, "zScoreIWD": -0.31}, "Birthday Escape": {"Name": "Birthday Escape", "Color": "U", "Rarity": "common", "# GIH": 180004, "OH WR": "57.8%", "GIH WR": "61.2%", "ATA": "5.29", "ALSA": "4.34", "IWD": "6.88pp", "zScoreGIH": 0.976, "zScoreOH": 0.647, "zScoreIWD": 0.904}, "Borne Upon a Wind": {"Name": "Borne Upon a Wind", "Color": "U", "Rarity": "rare", "# GIH": 2345, "OH WR": "45.5%", "GIH WR": "52.7%", "ATA": "8.33", "ALSA": "5.48", "IWD": "1.79pp", "zScoreGIH": -0.69, "zScoreOH": -1.26, "zScoreIWD": -0.27}, "Captain of Umbar": {"Name": "Captain of Umbar", "Color": "U", "Rarity": "common", "# GIH": 19863, "OH WR": "48.3%", "GIH WR": "52.3%", "ATA": "11.23", "ALSA": "7.68", "IWD": "1.42pp", "zScoreGIH": -0.77, "zScoreOH": -0.83, "zScoreIWD": -0.35}, "Council's Deliberation": {"Name": "Council's Deliberation", "Color": "U", "Rarity": "uncommon", "# GIH": 25492, "OH WR": "52.2%", "GIH WR": "55.2%", "ATA": "7.05", "ALSA": "5.07", "IWD": "3.7pp", "zScoreGIH": -0.2, "zScoreOH": -0.22, "zScoreIWD": 0.168}, "Deceive the Messenger": {"Name": "Deceive the Messenger", "Color": "U", "Rarity": "common", "# GIH": 126483, "OH WR": "56.1%", "GIH WR": "60.2%", "ATA": "8.12", "ALSA": "6.15", "IWD": "5.01pp", "zScoreGIH": 0.78, "zScoreOH": 0.382, "zScoreIWD": 0.471}, "Dreadful as the Storm": {"Name": "Dreadful as the Storm", "Color": "U", "Rarity": "common", "# GIH": 64376, "OH WR": "53.3%", "GIH WR": "59.8%", "ATA": "10.19", "ALSA": "7.54", "IWD": "4.65pp", "zScoreGIH": 0.701, "zScoreOH": -0.05, "zScoreIWD": 0.388}, "Elrond, Lord of Rivendell": {"Name": "Elrond, Lord of Rivendell", "Color": "U", "Rarity": "uncommon", "# GIH": 32280, "OH WR": "53.7%", "GIH WR": "56.4%", "ATA": "4.42", "ALSA": "3.48", "IWD": "5.28pp", "zScoreGIH": 0.033, "zScoreOH": 0.008, "zScoreIWD": 0.534}, "Gandalf, Friend of the Shire": {"Name": "Gandalf, Friend of the Shire", "Color": "U", "Rarity": "uncommon", "# GIH": 51922, "OH WR": "54.8%", "GIH WR": "58.1%", "ATA": "3.0", "ALSA": "2.7", "IWD": "4.74pp", "zScoreGIH": 0.367, "zScoreOH": 0.179, "zScoreIWD": 0.409}, "Glorious Gale": {"Name": "Glorious Gale", "Color": "U", "Rarity": "common", "# GIH": 156324, "OH WR": "57.4%", "GIH WR": "60.5%", "ATA": "6.1", "ALSA": "4.76", "IWD": "6.64pp", "zScoreGIH": 0.839, "zScoreOH": 0.584, "zScoreIWD": 0.849}, "Goldberry, River-Daughter": {"Name": "Goldberry, River-Daughter", "Color": "U", "Rarity": "rare", "# GIH": 9710, "OH WR": "56.1%", "GIH WR": "56.4%", "ATA": "5.65", "ALSA": "4.22", "IWD": "4.83pp", "zScoreGIH": 0.033, "zScoreOH": 0.382, "zScoreIWD": 0.43}, "Grey Havens Navigator": {"Name": "Grey Havens Navigator", "Color": "U", "Rarity": "common", "# GIH": 44462, "OH WR": "52.7%", "GIH WR": "55.9%", "ATA": "9.91", "ALSA": "6.74", "IWD": "3.43pp", "zScoreGIH": -0.06, "zScoreOH": -0.14, "zScoreIWD": 0.106}, "Hithlain Knots": {"Name": "Hithlain Knots", "Color": "U", "Rarity": "common", "# GIH": 99053, "OH WR": "52.9%", "GIH WR": "59.9%", "ATA": "8.28", "ALSA": "5.95", "IWD": "4.87pp", "zScoreGIH": 0.721, "zScoreOH": -0.11, "zScoreIWD": 0.439}, "Horses of the Bruinen": {"Name": "Horses of the Bruinen", "Color": "U", "Rarity": "uncommon", "# GIH": 58293, "OH WR": "56.5%", "GIH WR": "62.9%", "ATA": "5.16", "ALSA": "4.31", "IWD": "8.44pp", "zScoreGIH": 1.31, "zScoreOH": 0.444, "zScoreIWD": 1.265}, "Ioreth of the Healing House": {"Name": "Ioreth of the Healing House", "Color": "U", "Rarity": "uncommon", "# GIH": 23168, "OH WR": "52.5%", "GIH WR": "54.8%", "ATA": "7.98", "ALSA": "5.56", "IWD": "2.79pp", "zScoreGIH": -0.28, "zScoreOH": -0.17, "zScoreIWD": -0.04}, "Isolation at Orthanc": {"Name": "Isolation at Orthanc", "Color": "U", "Rarity": "common", "# GIH": 120717, "OH WR": "53.5%", "GIH WR": "60.3%", "ATA": "8.56", "ALSA": "6.37", "IWD": "4.36pp", "zScoreGIH": 0.799, "zScoreOH": -0.02, "zScoreIWD": 0.321}, "Ithilien Kingfisher": {"Name": "Ithilien Kingfisher", "Color": "U", "Rarity": "common", "# GIH": 77918, "OH WR": "51.6%", "GIH WR": "55.9%", "ATA": "7.71", "ALSA": "5.38", "IWD": "3.54pp", "zScoreGIH": -0.06, "zScoreOH": -0.31, "zScoreIWD": 0.131}, "Knights of Dol Amroth": {"Name": "Knights of Dol Amroth", "Color": "U", "Rarity": "common", "# GIH": 19266, "OH WR": "47.2%", "GIH WR": "52.8%", "ATA": "11.18", "ALSA": "7.53", "IWD": "3.2pp", "zScoreGIH": -0.67, "zScoreOH": -1.0, "zScoreIWD": 0.052}, "L\u00f3rien Revealed": {"Name": "L\u00f3rien Revealed", "Color": "U", "Rarity": "common", "# GIH": 164169, "OH WR": "55.3%", "GIH WR": "59.9%", "ATA": "6.16", "ALSA": "4.87", "IWD": "4.83pp", "zScoreGIH": 0.721, "zScoreOH": 0.257, "zScoreIWD": 0.43}, "Lost Isle Calling": {"Name": "Lost Isle Calling", "Color": "U", "Rarity": "rare", "# GIH": 798, "OH WR": "32.4%", "GIH WR": "42.5%", "ATA": "8.48", "ALSA": "5.49", "IWD": "-5.62pp", "zScoreGIH": -2.69, "zScoreOH": -3.3, "zScoreIWD": -1.98}, "Meneldor, Swift Savior": {"Name": "Meneldor, Swift Savior", "Color": "U", "Rarity": "uncommon", "# GIH": 30742, "OH WR": "51.7%", "GIH WR": "56.6%", "ATA": "4.83", "ALSA": "3.72", "IWD": "4.6pp", "zScoreGIH": 0.073, "zScoreOH": -0.3, "zScoreIWD": 0.376}, "Nimrodel Watcher": {"Name": "Nimrodel Watcher", "Color": "U", "Rarity": "common", "# GIH": 28753, "OH WR": "49.8%", "GIH WR": "52.4%", "ATA": "10.42", "ALSA": "7.14", "IWD": "2.53pp", "zScoreGIH": -0.75, "zScoreOH": -0.59, "zScoreIWD": -0.1}, "Pelargir Survivor": {"Name": "Pelargir Survivor", "Color": "U", "Rarity": "common", "# GIH": 161929, "OH WR": "58.5%", "GIH WR": "58.2%", "ATA": "7.06", "ALSA": "5.65", "IWD": "4.09pp", "zScoreGIH": 0.387, "zScoreOH": 0.756, "zScoreIWD": 0.258}, "Press the Enemy": {"Name": "Press the Enemy", "Color": "U", "Rarity": "rare", "# GIH": 6255, "OH WR": "47.1%", "GIH WR": "54.7%", "ATA": "6.23", "ALSA": "4.41", "IWD": "1.92pp", "zScoreGIH": -0.3, "zScoreOH": -1.01, "zScoreIWD": -0.24}, "Rangers of Ithilien": {"Name": "Rangers of Ithilien", "Color": "U", "Rarity": "rare", "# GIH": 20588, "OH WR": "62.7%", "GIH WR": "65.8%", "ATA": "1.83", "ALSA": "1.86", "IWD": "13.29pp", "zScoreGIH": 1.88, "zScoreOH": 1.41, "zScoreIWD": 2.388}, "Saruman the White": {"Name": "Saruman the White", "Color": "U", "Rarity": "uncommon", "# GIH": 35115, "OH WR": "52.9%", "GIH WR": "56.5%", "ATA": "4.25", "ALSA": "3.45", "IWD": "4.48pp", "zScoreGIH": 0.053, "zScoreOH": -0.11, "zScoreIWD": 0.349}, "Saruman's Trickery": {"Name": "Saruman's Trickery", "Color": "U", "Rarity": "uncommon", "# GIH": 68894, "OH WR": "61.6%", "GIH WR": "64.4%", "ATA": "4.03", "ALSA": "3.6", "IWD": "10.96pp", "zScoreGIH": 1.605, "zScoreOH": 1.239, "zScoreIWD": 1.848}, "Scroll of Isildur": {"Name": "Scroll of Isildur", "Color": "U", "Rarity": "rare", "# GIH": 18302, "OH WR": "57.7%", "GIH WR": "62.7%", "ATA": "3.12", "ALSA": "2.85", "IWD": "9.14pp", "zScoreGIH": 1.271, "zScoreOH": 0.631, "zScoreIWD": 1.427}, "Soothing of Sm\u00e9agol": {"Name": "Soothing of Sm\u00e9agol", "Color": "U", "Rarity": "common", "# GIH": 138719, "OH WR": "54.7%", "GIH WR": "61.2%", "ATA": "7.08", "ALSA": "5.31", "IWD": "6.42pp", "zScoreGIH": 0.976, "zScoreOH": 0.164, "zScoreIWD": 0.798}, "Stern Scolding": {"Name": "Stern Scolding", "Color": "U", "Rarity": "uncommon", "# GIH": 46410, "OH WR": "56.0%", "GIH WR": "56.2%", "ATA": "6.33", "ALSA": "4.93", "IWD": "3.58pp", "zScoreGIH": -0.0, "zScoreOH": 0.366, "zScoreIWD": 0.14}, "Storm of Saruman": {"Name": "Storm of Saruman", "Color": "U", "Rarity": "mythic", "# GIH": 2498, "OH WR": "45.1%", "GIH WR": "47.9%", "ATA": "5.01", "ALSA": "3.77", "IWD": "-0.39pp", "zScoreGIH": -1.63, "zScoreOH": -1.33, "zScoreIWD": -0.77}, "Surrounded by Orcs": {"Name": "Surrounded by Orcs", "Color": "U", "Rarity": "common", "# GIH": 35316, "OH WR": "47.3%", "GIH WR": "52.5%", "ATA": "10.12", "ALSA": "6.97", "IWD": "2.38pp", "zScoreGIH": -0.73, "zScoreOH": -0.98, "zScoreIWD": -0.13}, "Treason of Isengard": {"Name": "Treason of Isengard", "Color": "U", "Rarity": "common", "# GIH": 76210, "OH WR": "49.2%", "GIH WR": "55.7%", "ATA": "9.0", "ALSA": "6.44", "IWD": "1.84pp", "zScoreGIH": -0.1, "zScoreOH": -0.69, "zScoreIWD": -0.26}, "The Watcher in the Water": {"Name": "The Watcher in the Water", "Color": "U", "Rarity": "mythic", "# GIH": 1316, "OH WR": "39.0%", "GIH WR": "43.5%", "ATA": "5.26", "ALSA": "3.84", "IWD": "-2.88pp", "zScoreGIH": -2.5, "zScoreOH": -2.28, "zScoreIWD": -1.35}, "Willow-Wind": {"Name": "Willow-Wind", "Color": "U", "Rarity": "common", "# GIH": 32548, "OH WR": "50.1%", "GIH WR": "55.3%", "ATA": "10.4", "ALSA": "7.05", "IWD": "3.83pp", "zScoreGIH": -0.18, "zScoreOH": -0.55, "zScoreIWD": 0.198}, "Bitter Downfall": {"Name": "Bitter Downfall", "Color": "B", "Rarity": "uncommon", "# GIH": 57943, "OH WR": "56.9%", "GIH WR": "62.4%", "ATA": "2.37", "ALSA": "2.17", "IWD": "5.59pp", "zScoreGIH": 1.212, "zScoreOH": 0.507, "zScoreIWD": 0.605}, "The Black Breath": {"Name": "The Black Breath", "Color": "B", "Rarity": "common", "# GIH": 46386, "OH WR": "54.0%", "GIH WR": "58.5%", "ATA": "9.95", "ALSA": "6.96", "IWD": "2.72pp", "zScoreGIH": 0.446, "zScoreOH": 0.055, "zScoreIWD": -0.05}, "Call of the Ring": {"Name": "Call of the Ring", "Color": "B", "Rarity": "rare", "# GIH": 18318, "OH WR": "64.0%", "GIH WR": "58.7%", "ATA": "1.44", "ALSA": "1.46", "IWD": "6.74pp", "zScoreGIH": 0.485, "zScoreOH": 1.613, "zScoreIWD": 0.872}, "Cirith Ungol Patrol": {"Name": "Cirith Ungol Patrol", "Color": "B", "Rarity": "common", "# GIH": 79253, "OH WR": "54.1%", "GIH WR": "57.2%", "ATA": "8.47", "ALSA": "5.9", "IWD": "0.34pp", "zScoreGIH": 0.191, "zScoreOH": 0.07, "zScoreIWD": -0.6}, "Claim the Precious": {"Name": "Claim the Precious", "Color": "B", "Rarity": "common", "# GIH": 160521, "OH WR": "59.0%", "GIH WR": "63.4%", "ATA": "2.54", "ALSA": "2.31", "IWD": "6.77pp", "zScoreGIH": 1.408, "zScoreOH": 0.834, "zScoreIWD": 0.879}, "Dunland Crebain": {"Name": "Dunland Crebain", "Color": "B", "Rarity": "common", "# GIH": 178691, "OH WR": "60.7%", "GIH WR": "61.5%", "ATA": "3.43", "ALSA": "2.95", "IWD": "5.23pp", "zScoreGIH": 1.035, "zScoreOH": 1.098, "zScoreIWD": 0.522}, "Easterling Vanguard": {"Name": "Easterling Vanguard", "Color": "B", "Rarity": "common", "# GIH": 146177, "OH WR": "58.5%", "GIH WR": "58.4%", "ATA": "5.39", "ALSA": "4.03", "IWD": "1.73pp", "zScoreGIH": 0.426, "zScoreOH": 0.756, "zScoreIWD": -0.28}, "Gollum, Patient Plotter": {"Name": "Gollum, Patient Plotter", "Color": "B", "Rarity": "uncommon", "# GIH": 59370, "OH WR": "60.6%", "GIH WR": "60.4%", "ATA": "2.72", "ALSA": "2.43", "IWD": "5.1pp", "zScoreGIH": 0.819, "zScoreOH": 1.083, "zScoreIWD": 0.492}, "Gollum's Bite": {"Name": "Gollum's Bite", "Color": "B", "Rarity": "uncommon", "# GIH": 61315, "OH WR": "59.8%", "GIH WR": "62.2%", "ATA": "2.78", "ALSA": "2.5", "IWD": "5.66pp", "zScoreGIH": 1.173, "zScoreOH": 0.958, "zScoreIWD": 0.622}, "Gorbag of Minas Morgul": {"Name": "Gorbag of Minas Morgul", "Color": "B", "Rarity": "uncommon", "# GIH": 27882, "OH WR": "54.0%", "GIH WR": "55.2%", "ATA": "6.06", "ALSA": "4.24", "IWD": "0.41pp", "zScoreGIH": -0.2, "zScoreOH": 0.055, "zScoreIWD": -0.59}, "Gothmog, Morgul Lieutenant": {"Name": "Gothmog, Morgul Lieutenant", "Color": "B", "Rarity": "uncommon", "# GIH": 50843, "OH WR": "59.2%", "GIH WR": "61.4%", "ATA": "2.67", "ALSA": "2.39", "IWD": "5.71pp", "zScoreGIH": 1.016, "zScoreOH": 0.865, "zScoreIWD": 0.633}, "Gr\u00edma Wormtongue": {"Name": "Gr\u00edma Wormtongue", "Color": "B", "Rarity": "uncommon", "# GIH": 33194, "OH WR": "53.7%", "GIH WR": "56.3%", "ATA": "4.64", "ALSA": "3.54", "IWD": "1.16pp", "zScoreGIH": 0.014, "zScoreOH": 0.008, "zScoreIWD": -0.41}, "Grond, the Gatebreaker": {"Name": "Grond, the Gatebreaker", "Color": "B", "Rarity": "uncommon", "# GIH": 21469, "OH WR": "53.3%", "GIH WR": "54.8%", "ATA": "6.46", "ALSA": "4.69", "IWD": "-0.27pp", "zScoreGIH": -0.28, "zScoreOH": -0.05, "zScoreIWD": -0.75}, "Haunt of the Dead Marshes": {"Name": "Haunt of the Dead Marshes", "Color": "B", "Rarity": "common", "# GIH": 111340, "OH WR": "58.1%", "GIH WR": "58.4%", "ATA": "7.02", "ALSA": "5.02", "IWD": "2.54pp", "zScoreGIH": 0.426, "zScoreOH": 0.693, "zScoreIWD": -0.09}, "Isildur's Fateful Strike": {"Name": "Isildur's Fateful Strike", "Color": "B", "Rarity": "rare", "# GIH": 9904, "OH WR": "50.7%", "GIH WR": "55.3%", "ATA": "2.98", "ALSA": "2.64", "IWD": "0.48pp", "zScoreGIH": -0.18, "zScoreOH": -0.45, "zScoreIWD": -0.57}, "Lash of the Balrog": {"Name": "Lash of the Balrog", "Color": "B", "Rarity": "common", "# GIH": 122650, "OH WR": "53.8%", "GIH WR": "59.0%", "ATA": "5.11", "ALSA": "3.82", "IWD": "1.85pp", "zScoreGIH": 0.544, "zScoreOH": 0.024, "zScoreIWD": -0.25}, "Lobelia Sackville-Baggins": {"Name": "Lobelia Sackville-Baggins", "Color": "B", "Rarity": "rare", "# GIH": 12246, "OH WR": "53.4%", "GIH WR": "56.6%", "ATA": "2.69", "ALSA": "2.4", "IWD": "1.98pp", "zScoreGIH": 0.073, "zScoreOH": -0.03, "zScoreIWD": -0.22}, "March from the Black Gate": {"Name": "March from the Black Gate", "Color": "B", "Rarity": "uncommon", "# GIH": 46828, "OH WR": "63.0%", "GIH WR": "56.0%", "ATA": "2.83", "ALSA": "2.48", "IWD": "3.65pp", "zScoreGIH": -0.04, "zScoreOH": 1.457, "zScoreIWD": 0.156}, "Mirkwood Bats": {"Name": "Mirkwood Bats", "Color": "B", "Rarity": "common", "# GIH": 57817, "OH WR": "51.6%", "GIH WR": "55.0%", "ATA": "7.26", "ALSA": "4.92", "IWD": "-0.48pp", "zScoreGIH": -0.24, "zScoreOH": -0.31, "zScoreIWD": -0.79}, "Mordor Muster": {"Name": "Mordor Muster", "Color": "B", "Rarity": "common", "# GIH": 156341, "OH WR": "58.6%", "GIH WR": "58.6%", "ATA": "5.1", "ALSA": "3.89", "IWD": "2.31pp", "zScoreGIH": 0.466, "zScoreOH": 0.771, "zScoreIWD": -0.15}, "Mordor Trebuchet": {"Name": "Mordor Trebuchet", "Color": "B", "Rarity": "common", "# GIH": 47749, "OH WR": "51.4%", "GIH WR": "53.9%", "ATA": "8.21", "ALSA": "5.48", "IWD": "-1.17pp", "zScoreGIH": -0.45, "zScoreOH": -0.34, "zScoreIWD": -0.95}, "Morgul-Knife Wound": {"Name": "Morgul-Knife Wound", "Color": "B", "Rarity": "common", "# GIH": 36906, "OH WR": "54.1%", "GIH WR": "57.3%", "ATA": "9.47", "ALSA": "6.25", "IWD": "1.61pp", "zScoreGIH": 0.21, "zScoreOH": 0.07, "zScoreIWD": -0.31}, "Nasty End": {"Name": "Nasty End", "Color": "B", "Rarity": "common", "# GIH": 81613, "OH WR": "52.4%", "GIH WR": "56.2%", "ATA": "8.21", "ALSA": "5.7", "IWD": "-0.76pp", "zScoreGIH": -0.0, "zScoreOH": -0.19, "zScoreIWD": -0.86}, "Nazg\u00fbl": {"Name": "Nazg\u00fbl", "Color": "B", "Rarity": "uncommon", "# GIH": 60156, "OH WR": "62.9%", "GIH WR": "63.3%", "ATA": "2.12", "ALSA": "2.02", "IWD": "8.19pp", "zScoreGIH": 1.389, "zScoreOH": 1.441, "zScoreIWD": 1.207}, "Oath of the Grey Host": {"Name": "Oath of the Grey Host", "Color": "B", "Rarity": "uncommon", "# GIH": 37491, "OH WR": "55.5%", "GIH WR": "57.4%", "ATA": "4.7", "ALSA": "3.67", "IWD": "2.22pp", "zScoreGIH": 0.23, "zScoreOH": 0.288, "zScoreIWD": -0.17}, "One Ring to Rule Them All": {"Name": "One Ring to Rule Them All", "Color": "B", "Rarity": "rare", "# GIH": 9738, "OH WR": "50.5%", "GIH WR": "56.8%", "ATA": "2.68", "ALSA": "2.46", "IWD": "2.62pp", "zScoreGIH": 0.112, "zScoreOH": -0.48, "zScoreIWD": -0.08}, "Orcish Bowmasters": {"Name": "Orcish Bowmasters", "Color": "B", "Rarity": "rare", "# GIH": 21098, "OH WR": "72.7%", "GIH WR": "70.3%", "ATA": "1.3", "ALSA": "1.31", "IWD": "17.14pp", "zScoreGIH": 2.764, "zScoreOH": 2.968, "zScoreIWD": 3.279}, "Orcish Medicine": {"Name": "Orcish Medicine", "Color": "B", "Rarity": "common", "# GIH": 43582, "OH WR": "53.1%", "GIH WR": "57.2%", "ATA": "9.28", "ALSA": "6.17", "IWD": "1.07pp", "zScoreGIH": 0.191, "zScoreOH": -0.08, "zScoreIWD": -0.44}, "Sam's Desperate Rescue": {"Name": "Sam's Desperate Rescue", "Color": "B", "Rarity": "common", "# GIH": 117781, "OH WR": "54.6%", "GIH WR": "60.5%", "ATA": "7.31", "ALSA": "5.35", "IWD": "2.17pp", "zScoreGIH": 0.839, "zScoreOH": 0.148, "zScoreIWD": -0.18}, "Sauron, the Necromancer": {"Name": "Sauron, the Necromancer", "Color": "B", "Rarity": "rare", "# GIH": 14942, "OH WR": "54.9%", "GIH WR": "58.7%", "ATA": "1.5", "ALSA": "1.52", "IWD": "3.85pp", "zScoreGIH": 0.485, "zScoreOH": 0.195, "zScoreIWD": 0.203}, "Shadow of the Enemy": {"Name": "Shadow of the Enemy", "Color": "B", "Rarity": "mythic", "# GIH": 1875, "OH WR": "44.0%", "GIH WR": "55.2%", "ATA": "5.12", "ALSA": "3.72", "IWD": "-0.72pp", "zScoreGIH": -0.2, "zScoreOH": -1.5, "zScoreIWD": -0.85}, "Shelob's Ambush": {"Name": "Shelob's Ambush", "Color": "B", "Rarity": "common", "# GIH": 101773, "OH WR": "57.7%", "GIH WR": "61.0%", "ATA": "8.17", "ALSA": "5.93", "IWD": "3.09pp", "zScoreGIH": 0.937, "zScoreOH": 0.631, "zScoreIWD": 0.027}, "Snarling Warg": {"Name": "Snarling Warg", "Color": "B", "Rarity": "common", "# GIH": 34915, "OH WR": "54.7%", "GIH WR": "56.2%", "ATA": "9.87", "ALSA": "6.63", "IWD": "0.56pp", "zScoreGIH": -0.0, "zScoreOH": 0.164, "zScoreIWD": -0.55}, "The Torment of Gollum": {"Name": "The Torment of Gollum", "Color": "B", "Rarity": "common", "# GIH": 171539, "OH WR": "60.2%", "GIH WR": "61.2%", "ATA": "5.41", "ALSA": "4.48", "IWD": "4.55pp", "zScoreGIH": 0.976, "zScoreOH": 1.021, "zScoreIWD": 0.365}, "Troll of Khazad-d\u00fbm": {"Name": "Troll of Khazad-d\u00fbm", "Color": "B", "Rarity": "common", "# GIH": 139943, "OH WR": "56.5%", "GIH WR": "59.2%", "ATA": "5.57", "ALSA": "4.13", "IWD": "2.37pp", "zScoreGIH": 0.583, "zScoreOH": 0.444, "zScoreIWD": -0.13}, "Uruk-hai Berserker": {"Name": "Uruk-hai Berserker", "Color": "B", "Rarity": "common", "# GIH": 153355, "OH WR": "58.1%", "GIH WR": "59.9%", "ATA": "5.2", "ALSA": "3.99", "IWD": "3.07pp", "zScoreGIH": 0.721, "zScoreOH": 0.693, "zScoreIWD": 0.022}, "Voracious Fell Beast": {"Name": "Voracious Fell Beast", "Color": "B", "Rarity": "uncommon", "# GIH": 57259, "OH WR": "59.5%", "GIH WR": "63.5%", "ATA": "2.65", "ALSA": "2.45", "IWD": "6.76pp", "zScoreGIH": 1.428, "zScoreOH": 0.912, "zScoreIWD": 0.876}, "Witch-king of Angmar": {"Name": "Witch-king of Angmar", "Color": "B", "Rarity": "mythic", "# GIH": 9956, "OH WR": "67.8%", "GIH WR": "66.6%", "ATA": "1.18", "ALSA": "1.18", "IWD": "14.89pp", "zScoreGIH": 2.037, "zScoreOH": 2.204, "zScoreIWD": 2.758}, "Battle-Scarred Goblin": {"Name": "Battle-Scarred Goblin", "Color": "R", "Rarity": "common", "# GIH": 96655, "OH WR": "57.5%", "GIH WR": "55.8%", "ATA": "7.8", "ALSA": "5.51", "IWD": "-0.24pp", "zScoreGIH": -0.08, "zScoreOH": 0.6, "zScoreIWD": -0.74}, "Book of Mazarbul": {"Name": "Book of Mazarbul", "Color": "R", "Rarity": "uncommon", "# GIH": 49101, "OH WR": "60.1%", "GIH WR": "59.3%", "ATA": "3.63", "ALSA": "3.07", "IWD": "2.98pp", "zScoreGIH": 0.603, "zScoreOH": 1.005, "zScoreIWD": 0.001}, "Breaking of the Fellowship": {"Name": "Breaking of the Fellowship", "Color": "R", "Rarity": "common", "# GIH": 79043, "OH WR": "54.6%", "GIH WR": "59.0%", "ATA": "8.02", "ALSA": "5.6", "IWD": "2.54pp", "zScoreGIH": 0.544, "zScoreOH": 0.148, "zScoreIWD": -0.09}, "Cast into the Fire": {"Name": "Cast into the Fire", "Color": "R", "Rarity": "common", "# GIH": 25057, "OH WR": "52.1%", "GIH WR": "55.9%", "ATA": "10.8", "ALSA": "7.52", "IWD": "0.5pp", "zScoreGIH": -0.06, "zScoreOH": -0.24, "zScoreIWD": -0.57}, "Display of Power": {"Name": "Display of Power", "Color": "R", "Rarity": "rare", "# GIH": 1798, "OH WR": "42.9%", "GIH WR": "50.4%", "ATA": "8.56", "ALSA": "5.63", "IWD": "-4.62pp", "zScoreGIH": -1.14, "zScoreOH": -1.67, "zScoreIWD": -1.75}, "\u00c9omer, Marshal of Rohan": {"Name": "\u00c9omer, Marshal of Rohan", "Color": "R", "Rarity": "rare", "# GIH": 13507, "OH WR": "57.2%", "GIH WR": "58.9%", "ATA": "2.1", "ALSA": "2.01", "IWD": "3.48pp", "zScoreGIH": 0.524, "zScoreOH": 0.553, "zScoreIWD": 0.117}, "\u00c9omer of the Riddermark": {"Name": "\u00c9omer of the Riddermark", "Color": "R", "Rarity": "uncommon", "# GIH": 62634, "OH WR": "62.6%", "GIH WR": "63.8%", "ATA": "2.65", "ALSA": "2.51", "IWD": "7.9pp", "zScoreGIH": 1.487, "zScoreOH": 1.394, "zScoreIWD": 1.14}, "Erebor Flamesmith": {"Name": "Erebor Flamesmith", "Color": "R", "Rarity": "common", "# GIH": 105496, "OH WR": "55.3%", "GIH WR": "56.4%", "ATA": "7.63", "ALSA": "5.52", "IWD": "1.17pp", "zScoreGIH": 0.033, "zScoreOH": 0.257, "zScoreIWD": -0.41}, "Erkenbrand, Lord of Westfold": {"Name": "Erkenbrand, Lord of Westfold", "Color": "R", "Rarity": "uncommon", "# GIH": 33958, "OH WR": "54.9%", "GIH WR": "56.6%", "ATA": "4.69", "ALSA": "3.75", "IWD": "0.28pp", "zScoreGIH": 0.073, "zScoreOH": 0.195, "zScoreIWD": -0.62}, "Fall of Cair Andros": {"Name": "Fall of Cair Andros", "Color": "R", "Rarity": "rare", "# GIH": 6966, "OH WR": "49.9%", "GIH WR": "55.1%", "ATA": "4.38", "ALSA": "3.5", "IWD": "0.69pp", "zScoreGIH": -0.22, "zScoreOH": -0.58, "zScoreIWD": -0.52}, "Fear, Fire, Foes!": {"Name": "Fear, Fire, Foes!", "Color": "R", "Rarity": "uncommon", "# GIH": 69699, "OH WR": "61.1%", "GIH WR": "64.4%", "ATA": "2.32", "ALSA": "2.23", "IWD": "7.88pp", "zScoreGIH": 1.605, "zScoreOH": 1.161, "zScoreIWD": 1.136}, "Fiery Inscription": {"Name": "Fiery Inscription", "Color": "R", "Rarity": "uncommon", "# GIH": 50591, "OH WR": "56.3%", "GIH WR": "59.5%", "ATA": "4.37", "ALSA": "3.9", "IWD": "4.54pp", "zScoreGIH": 0.642, "zScoreOH": 0.413, "zScoreIWD": 0.362}, "Fire of Orthanc": {"Name": "Fire of Orthanc", "Color": "R", "Rarity": "common", "# GIH": 3595, "OH WR": "48.7%", "GIH WR": "50.5%", "ATA": "12.38", "ALSA": "8.66", "IWD": "-3.58pp", "zScoreGIH": -1.12, "zScoreOH": -0.77, "zScoreIWD": -1.51}, "Foray of Orcs": {"Name": "Foray of Orcs", "Color": "R", "Rarity": "uncommon", "# GIH": 63004, "OH WR": "58.8%", "GIH WR": "61.1%", "ATA": "2.91", "ALSA": "2.62", "IWD": "4.2pp", "zScoreGIH": 0.957, "zScoreOH": 0.803, "zScoreIWD": 0.284}, "Gimli, Counter of Kills": {"Name": "Gimli, Counter of Kills", "Color": "R", "Rarity": "uncommon", "# GIH": 19386, "OH WR": "53.7%", "GIH WR": "56.0%", "ATA": "6.44", "ALSA": "4.47", "IWD": "1.17pp", "zScoreGIH": -0.04, "zScoreOH": 0.008, "zScoreIWD": -0.41}, "Gimli's Axe": {"Name": "Gimli's Axe", "Color": "R", "Rarity": "common", "# GIH": 8092, "OH WR": "49.5%", "GIH WR": "53.4%", "ATA": "11.98", "ALSA": "8.3", "IWD": "-2.65pp", "zScoreGIH": -0.55, "zScoreOH": -0.64, "zScoreIWD": -1.3}, "Gimli's Fury": {"Name": "Gimli's Fury", "Color": "R", "Rarity": "common", "# GIH": 17601, "OH WR": "53.0%", "GIH WR": "55.1%", "ATA": "11.26", "ALSA": "7.8", "IWD": "-0.67pp", "zScoreGIH": -0.22, "zScoreOH": -0.1, "zScoreIWD": -0.84}, "Gl\u00f3in, Dwarf Emissary": {"Name": "Gl\u00f3in, Dwarf Emissary", "Color": "R", "Rarity": "rare", "# GIH": 11295, "OH WR": "55.5%", "GIH WR": "55.9%", "ATA": "3.57", "ALSA": "3.0", "IWD": "1.01pp", "zScoreGIH": -0.06, "zScoreOH": 0.288, "zScoreIWD": -0.45}, "Goblin Fireleaper": {"Name": "Goblin Fireleaper", "Color": "R", "Rarity": "uncommon", "# GIH": 41190, "OH WR": "55.2%", "GIH WR": "56.1%", "ATA": "5.41", "ALSA": "4.04", "IWD": "-0.69pp", "zScoreGIH": -0.02, "zScoreOH": 0.242, "zScoreIWD": -0.84}, "Grishn\u00e1kh, Brash Instigator": {"Name": "Grishn\u00e1kh, Brash Instigator", "Color": "R", "Rarity": "uncommon", "# GIH": 57661, "OH WR": "60.9%", "GIH WR": "62.3%", "ATA": "3.03", "ALSA": "2.71", "IWD": "5.77pp", "zScoreGIH": 1.192, "zScoreOH": 1.13, "zScoreIWD": 0.647}, "Haradrim Spearmaster": {"Name": "Haradrim Spearmaster", "Color": "R", "Rarity": "common", "# GIH": 80630, "OH WR": "56.3%", "GIH WR": "56.5%", "ATA": "8.14", "ALSA": "5.68", "IWD": "-0.07pp", "zScoreGIH": 0.053, "zScoreOH": 0.413, "zScoreIWD": -0.7}, "Hew the Entwood": {"Name": "Hew the Entwood", "Color": "R", "Rarity": "mythic", "# GIH": 50, "OH WR": "11.8%", "GIH WR": "18.2%", "ATA": "8.16", "ALSA": "5.29", "IWD": "-26.72pp", "zScoreGIH": -7.47, "zScoreOH": -6.51, "zScoreIWD": -6.87}, "Improvised Club": {"Name": "Improvised Club", "Color": "R", "Rarity": "common", "# GIH": 135215, "OH WR": "54.6%", "GIH WR": "60.5%", "ATA": "6.22", "ALSA": "4.68", "IWD": "2.15pp", "zScoreGIH": 0.839, "zScoreOH": 0.148, "zScoreIWD": -0.19}, "Moria Marauder": {"Name": "Moria Marauder", "Color": "R", "Rarity": "rare", "# GIH": 15103, "OH WR": "59.3%", "GIH WR": "56.1%", "ATA": "2.74", "ALSA": "2.55", "IWD": "1.72pp", "zScoreGIH": -0.02, "zScoreOH": 0.88, "zScoreIWD": -0.28}, "Oliphaunt": {"Name": "Oliphaunt", "Color": "R", "Rarity": "common", "# GIH": 109663, "OH WR": "54.9%", "GIH WR": "57.0%", "ATA": "7.15", "ALSA": "5.03", "IWD": "0.42pp", "zScoreGIH": 0.151, "zScoreOH": 0.195, "zScoreIWD": -0.59}, "Olog-hai Crusher": {"Name": "Olog-hai Crusher", "Color": "R", "Rarity": "common", "# GIH": 26799, "OH WR": "53.3%", "GIH WR": "54.2%", "ATA": "10.41", "ALSA": "7.11", "IWD": "-1.5pp", "zScoreGIH": -0.39, "zScoreOH": -0.05, "zScoreIWD": -1.03}, "Quarrel's End": {"Name": "Quarrel's End", "Color": "R", "Rarity": "common", "# GIH": 133968, "OH WR": "57.0%", "GIH WR": "59.7%", "ATA": "7.44", "ALSA": "5.64", "IWD": "2.52pp", "zScoreGIH": 0.682, "zScoreOH": 0.522, "zScoreIWD": -0.1}, "Rally at the Hornburg": {"Name": "Rally at the Hornburg", "Color": "R", "Rarity": "common", "# GIH": 194884, "OH WR": "61.5%", "GIH WR": "61.3%", "ATA": "4.77", "ALSA": "4.05", "IWD": "4.74pp", "zScoreGIH": 0.996, "zScoreOH": 1.223, "zScoreIWD": 0.409}, "Ranger's Firebrand": {"Name": "Ranger's Firebrand", "Color": "R", "Rarity": "uncommon", "# GIH": 60911, "OH WR": "59.5%", "GIH WR": "61.8%", "ATA": "2.86", "ALSA": "2.57", "IWD": "5.09pp", "zScoreGIH": 1.094, "zScoreOH": 0.912, "zScoreIWD": 0.49}, "Relentless Rohirrim": {"Name": "Relentless Rohirrim", "Color": "R", "Rarity": "common", "# GIH": 126697, "OH WR": "57.3%", "GIH WR": "59.0%", "ATA": "6.92", "ALSA": "5.19", "IWD": "1.7pp", "zScoreGIH": 0.544, "zScoreOH": 0.569, "zScoreIWD": -0.29}, "Rising of the Day": {"Name": "Rising of the Day", "Color": "R", "Rarity": "uncommon", "# GIH": 1366, "OH WR": "46.0%", "GIH WR": "45.5%", "ATA": "11.19", "ALSA": "7.24", "IWD": "-5.28pp", "zScoreGIH": -2.1, "zScoreOH": -1.19, "zScoreIWD": -1.91}, "Rohirrim Lancer": {"Name": "Rohirrim Lancer", "Color": "R", "Rarity": "common", "# GIH": 129101, "OH WR": "58.3%", "GIH WR": "56.2%", "ATA": "6.65", "ALSA": "5.01", "IWD": "0.68pp", "zScoreGIH": -0.0, "zScoreOH": 0.725, "zScoreIWD": -0.53}, "Rush the Room": {"Name": "Rush the Room", "Color": "R", "Rarity": "common", "# GIH": 5848, "OH WR": "52.3%", "GIH WR": "52.7%", "ATA": "12.12", "ALSA": "8.47", "IWD": "-0.84pp", "zScoreGIH": -0.69, "zScoreOH": -0.2, "zScoreIWD": -0.88}, "Smite the Deathless": {"Name": "Smite the Deathless", "Color": "R", "Rarity": "common", "# GIH": 160568, "OH WR": "57.9%", "GIH WR": "60.0%", "ATA": "3.2", "ALSA": "2.74", "IWD": "3.54pp", "zScoreGIH": 0.741, "zScoreOH": 0.662, "zScoreIWD": 0.131}, "Spiteful Banditry": {"Name": "Spiteful Banditry", "Color": "R", "Rarity": "mythic", "# GIH": 8265, "OH WR": "57.1%", "GIH WR": "60.9%", "ATA": "1.68", "ALSA": "1.72", "IWD": "5.72pp", "zScoreGIH": 0.917, "zScoreOH": 0.538, "zScoreIWD": 0.636}, "Swarming of Moria": {"Name": "Swarming of Moria", "Color": "R", "Rarity": "common", "# GIH": 98512, "OH WR": "55.1%", "GIH WR": "56.6%", "ATA": "7.3", "ALSA": "5.19", "IWD": "1.52pp", "zScoreGIH": 0.073, "zScoreOH": 0.226, "zScoreIWD": -0.33}, "There and Back Again": {"Name": "There and Back Again", "Color": "R", "Rarity": "rare", "# GIH": 16696, "OH WR": "58.9%", "GIH WR": "59.7%", "ATA": "1.81", "ALSA": "1.82", "IWD": "5.18pp", "zScoreGIH": 0.682, "zScoreOH": 0.818, "zScoreIWD": 0.511}, "Warbeast of Gorgoroth": {"Name": "Warbeast of Gorgoroth", "Color": "R", "Rarity": "common", "# GIH": 70319, "OH WR": "56.6%", "GIH WR": "58.5%", "ATA": "8.53", "ALSA": "5.94", "IWD": "1.77pp", "zScoreGIH": 0.446, "zScoreOH": 0.46, "zScoreIWD": -0.27}, "Bag End Porter": {"Name": "Bag End Porter", "Color": "G", "Rarity": "common", "# GIH": 34933, "OH WR": "53.8%", "GIH WR": "55.9%", "ATA": "10.29", "ALSA": "7.05", "IWD": "3.01pp", "zScoreGIH": -0.06, "zScoreOH": 0.024, "zScoreIWD": 0.008}, "Bombadil's Song": {"Name": "Bombadil's Song", "Color": "G", "Rarity": "common", "# GIH": 24677, "OH WR": "47.8%", "GIH WR": "54.2%", "ATA": "11.15", "ALSA": "7.59", "IWD": "1.64pp", "zScoreGIH": -0.39, "zScoreOH": -0.91, "zScoreIWD": -0.3}, "Brandywine Farmer": {"Name": "Brandywine Farmer", "Color": "G", "Rarity": "common", "# GIH": 9814, "OH WR": "45.3%", "GIH WR": "48.4%", "ATA": "12.21", "ALSA": "8.28", "IWD": "-3.18pp", "zScoreGIH": -1.53, "zScoreOH": -1.29, "zScoreIWD": -1.42}, "Celeborn the Wise": {"Name": "Celeborn the Wise", "Color": "G", "Rarity": "uncommon", "# GIH": 12627, "OH WR": "52.0%", "GIH WR": "53.4%", "ATA": "6.98", "ALSA": "4.75", "IWD": "4.36pp", "zScoreGIH": -0.55, "zScoreOH": -0.25, "zScoreIWD": 0.321}, "Chance-Met Elves": {"Name": "Chance-Met Elves", "Color": "G", "Rarity": "common", "# GIH": 24914, "OH WR": "50.8%", "GIH WR": "50.7%", "ATA": "10.29", "ALSA": "6.84", "IWD": "1.99pp", "zScoreGIH": -1.08, "zScoreOH": -0.44, "zScoreIWD": -0.22}, "Delighted Halfling": {"Name": "Delighted Halfling", "Color": "G", "Rarity": "rare", "# GIH": 10565, "OH WR": "64.4%", "GIH WR": "56.2%", "ATA": "2.53", "ALSA": "2.35", "IWD": "8.14pp", "zScoreGIH": -0.0, "zScoreOH": 1.675, "zScoreIWD": 1.196}, "D\u00fanedain Rangers": {"Name": "D\u00fanedain Rangers", "Color": "G", "Rarity": "uncommon", "# GIH": 21182, "OH WR": "53.0%", "GIH WR": "56.1%", "ATA": "6.47", "ALSA": "4.65", "IWD": "3.17pp", "zScoreGIH": -0.02, "zScoreOH": -0.1, "zScoreIWD": 0.045}, "Elven Chorus": {"Name": "Elven Chorus", "Color": "G", "Rarity": "rare", "# GIH": 7076, "OH WR": "48.8%", "GIH WR": "52.9%", "ATA": "3.48", "ALSA": "2.93", "IWD": "0.3pp", "zScoreGIH": -0.65, "zScoreOH": -0.75, "zScoreIWD": -0.61}, "Elven Farsight": {"Name": "Elven Farsight", "Color": "G", "Rarity": "common", "# GIH": 16705, "OH WR": "48.7%", "GIH WR": "52.6%", "ATA": "11.44", "ALSA": "7.61", "IWD": "1.69pp", "zScoreGIH": -0.71, "zScoreOH": -0.77, "zScoreIWD": -0.29}, "Enraged Huorn": {"Name": "Enraged Huorn", "Color": "G", "Rarity": "common", "# GIH": 58399, "OH WR": "53.3%", "GIH WR": "57.7%", "ATA": "9.18", "ALSA": "6.44", "IWD": "3.7pp", "zScoreGIH": 0.289, "zScoreOH": -0.05, "zScoreIWD": 0.168}, "Entish Restoration": {"Name": "Entish Restoration", "Color": "G", "Rarity": "uncommon", "# GIH": 8519, "OH WR": "44.4%", "GIH WR": "48.1%", "ATA": "8.8", "ALSA": "5.87", "IWD": "-3.26pp", "zScoreGIH": -1.59, "zScoreOH": -1.44, "zScoreIWD": -1.44}, "Ent's Fury": {"Name": "Ent's Fury", "Color": "G", "Rarity": "common", "# GIH": 67142, "OH WR": "52.2%", "GIH WR": "57.9%", "ATA": "7.82", "ALSA": "5.57", "IWD": "3.46pp", "zScoreGIH": 0.328, "zScoreOH": -0.22, "zScoreIWD": 0.112}, "Fall of Gil-galad": {"Name": "Fall of Gil-galad", "Color": "G", "Rarity": "rare", "# GIH": 9339, "OH WR": "54.4%", "GIH WR": "58.0%", "ATA": "3.11", "ALSA": "2.69", "IWD": "6.03pp", "zScoreGIH": 0.348, "zScoreOH": 0.117, "zScoreIWD": 0.707}, "Fangorn, Tree Shepherd": {"Name": "Fangorn, Tree Shepherd", "Color": "G", "Rarity": "rare", "# GIH": 2438, "OH WR": "47.7%", "GIH WR": "48.5%", "ATA": "6.51", "ALSA": "4.36", "IWD": "-1.39pp", "zScoreGIH": -1.51, "zScoreOH": -0.92, "zScoreIWD": -1.0}, "Galadhrim Bow": {"Name": "Galadhrim Bow", "Color": "G", "Rarity": "common", "# GIH": 8515, "OH WR": "49.8%", "GIH WR": "54.8%", "ATA": "12.27", "ALSA": "8.38", "IWD": "1.44pp", "zScoreGIH": -0.28, "zScoreOH": -0.59, "zScoreIWD": -0.35}, "Galadhrim Guide": {"Name": "Galadhrim Guide", "Color": "G", "Rarity": "common", "# GIH": 15270, "OH WR": "49.8%", "GIH WR": "52.2%", "ATA": "11.44", "ALSA": "7.61", "IWD": "2.55pp", "zScoreGIH": -0.79, "zScoreOH": -0.59, "zScoreIWD": -0.09}, "Generous Ent": {"Name": "Generous Ent", "Color": "G", "Rarity": "common", "# GIH": 80502, "OH WR": "53.5%", "GIH WR": "57.0%", "ATA": "7.43", "ALSA": "5.29", "IWD": "3.17pp", "zScoreGIH": 0.151, "zScoreOH": -0.02, "zScoreIWD": 0.045}, "Gift of Strands": {"Name": "Gift of Strands", "Color": "G", "Rarity": "uncommon", "# GIH": 7271, "OH WR": "51.9%", "GIH WR": "54.9%", "ATA": "9.53", "ALSA": "6.26", "IWD": "4.83pp", "zScoreGIH": -0.26, "zScoreOH": -0.27, "zScoreIWD": 0.43}, "Glorfindel, Dauntless Rescuer": {"Name": "Glorfindel, Dauntless Rescuer", "Color": "G", "Rarity": "uncommon", "# GIH": 10060, "OH WR": "48.2%", "GIH WR": "51.7%", "ATA": "7.94", "ALSA": "5.29", "IWD": "1.04pp", "zScoreGIH": -0.88, "zScoreOH": -0.84, "zScoreIWD": -0.44}, "Last March of the Ents": {"Name": "Last March of the Ents", "Color": "G", "Rarity": "mythic", "# GIH": 830, "OH WR": "38.9%", "GIH WR": "49.2%", "ATA": "6.09", "ALSA": "4.08", "IWD": "-3.65pp", "zScoreGIH": -1.38, "zScoreOH": -2.29, "zScoreIWD": -1.53}, "Legolas, Master Archer": {"Name": "Legolas, Master Archer", "Color": "G", "Rarity": "rare", "# GIH": 8395, "OH WR": "52.5%", "GIH WR": "54.1%", "ATA": "2.86", "ALSA": "2.58", "IWD": "3.38pp", "zScoreGIH": -0.41, "zScoreOH": -0.17, "zScoreIWD": 0.094}, "Long List of the Ents": {"Name": "Long List of the Ents", "Color": "G", "Rarity": "uncommon", "# GIH": 2330, "OH WR": "53.9%", "GIH WR": "43.8%", "ATA": "11.05", "ALSA": "7.29", "IWD": "-0.69pp", "zScoreGIH": -2.44, "zScoreOH": 0.039, "zScoreIWD": -0.84}, "Lothl\u00f3rien Lookout": {"Name": "Lothl\u00f3rien Lookout", "Color": "G", "Rarity": "common", "# GIH": 34206, "OH WR": "53.0%", "GIH WR": "51.5%", "ATA": "10.13", "ALSA": "6.88", "IWD": "2.1pp", "zScoreGIH": -0.92, "zScoreOH": -0.1, "zScoreIWD": -0.2}, "Many Partings": {"Name": "Many Partings", "Color": "G", "Rarity": "common", "# GIH": 59949, "OH WR": "55.6%", "GIH WR": "55.6%", "ATA": "9.17", "ALSA": "6.57", "IWD": "3.46pp", "zScoreGIH": -0.12, "zScoreOH": 0.304, "zScoreIWD": 0.112}, "Meriadoc Brandybuck": {"Name": "Meriadoc Brandybuck", "Color": "G", "Rarity": "uncommon", "# GIH": 24078, "OH WR": "57.2%", "GIH WR": "55.4%", "ATA": "6.08", "ALSA": "4.44", "IWD": "4.76pp", "zScoreGIH": -0.16, "zScoreOH": 0.553, "zScoreIWD": 0.413}, "Mirkwood Spider": {"Name": "Mirkwood Spider", "Color": "G", "Rarity": "common", "# GIH": 42216, "OH WR": "54.6%", "GIH WR": "54.7%", "ATA": "9.73", "ALSA": "6.55", "IWD": "2.5pp", "zScoreGIH": -0.3, "zScoreOH": 0.148, "zScoreIWD": -0.1}, "Mirrormere Guardian": {"Name": "Mirrormere Guardian", "Color": "G", "Rarity": "common", "# GIH": 48909, "OH WR": "54.1%", "GIH WR": "56.2%", "ATA": "9.97", "ALSA": "6.96", "IWD": "2.66pp", "zScoreGIH": -0.0, "zScoreOH": 0.07, "zScoreIWD": -0.07}, "Mushroom Watchdogs": {"Name": "Mushroom Watchdogs", "Color": "G", "Rarity": "common", "# GIH": 40804, "OH WR": "54.1%", "GIH WR": "53.3%", "ATA": "9.75", "ALSA": "6.78", "IWD": "1.39pp", "zScoreGIH": -0.57, "zScoreOH": 0.07, "zScoreIWD": -0.36}, "Peregrin Took": {"Name": "Peregrin Took", "Color": "G", "Rarity": "uncommon", "# GIH": 20338, "OH WR": "52.1%", "GIH WR": "53.2%", "ATA": "5.75", "ALSA": "4.21", "IWD": "1.59pp", "zScoreGIH": -0.59, "zScoreOH": -0.24, "zScoreIWD": -0.31}, "Pippin's Bravery": {"Name": "Pippin's Bravery", "Color": "G", "Rarity": "common", "# GIH": 10071, "OH WR": "50.2%", "GIH WR": "53.8%", "ATA": "12.34", "ALSA": "8.58", "IWD": "1.35pp", "zScoreGIH": -0.47, "zScoreOH": -0.53, "zScoreIWD": -0.37}, "Quickbeam, Upstart Ent": {"Name": "Quickbeam, Upstart Ent", "Color": "G", "Rarity": "uncommon", "# GIH": 24794, "OH WR": "51.4%", "GIH WR": "57.2%", "ATA": "5.45", "ALSA": "4.11", "IWD": "3.66pp", "zScoreGIH": 0.191, "zScoreOH": -0.34, "zScoreIWD": 0.159}, "Radagast the Brown": {"Name": "Radagast the Brown", "Color": "G", "Rarity": "mythic", "# GIH": 6305, "OH WR": "61.5%", "GIH WR": "60.9%", "ATA": "1.91", "ALSA": "1.93", "IWD": "9.6pp", "zScoreGIH": 0.917, "zScoreOH": 1.223, "zScoreIWD": 1.534}, "Revive the Shire": {"Name": "Revive the Shire", "Color": "G", "Rarity": "common", "# GIH": 14672, "OH WR": "48.1%", "GIH WR": "54.6%", "ATA": "11.99", "ALSA": "8.28", "IWD": "1.61pp", "zScoreGIH": -0.31, "zScoreOH": -0.86, "zScoreIWD": -0.31}, "The Ring Goes South": {"Name": "The Ring Goes South", "Color": "G", "Rarity": "rare", "# GIH": 446, "OH WR": "27.3%", "GIH WR": "39.8%", "ATA": "8.79", "ALSA": "5.53", "IWD": "-8.34pp", "zScoreGIH": -3.22, "zScoreOH": -4.1, "zScoreIWD": -2.61}, "Shortcut to Mushrooms": {"Name": "Shortcut to Mushrooms", "Color": "G", "Rarity": "uncommon", "# GIH": 6513, "OH WR": "42.0%", "GIH WR": "47.3%", "ATA": "9.34", "ALSA": "6.08", "IWD": "-4.85pp", "zScoreGIH": -1.75, "zScoreOH": -1.81, "zScoreIWD": -1.81}, "Shower of Arrows": {"Name": "Shower of Arrows", "Color": "G", "Rarity": "common", "# GIH": 3296, "OH WR": "44.4%", "GIH WR": "49.6%", "ATA": "12.84", "ALSA": "8.65", "IWD": "0.23pp", "zScoreGIH": -1.3, "zScoreOH": -1.44, "zScoreIWD": -0.63}, "Stew the Coneys": {"Name": "Stew the Coneys", "Color": "G", "Rarity": "uncommon", "# GIH": 27086, "OH WR": "51.7%", "GIH WR": "57.4%", "ATA": "5.23", "ALSA": "3.93", "IWD": "3.28pp", "zScoreGIH": 0.23, "zScoreOH": -0.3, "zScoreIWD": 0.071}, "Wose Pathfinder": {"Name": "Wose Pathfinder", "Color": "G", "Rarity": "common", "# GIH": 80507, "OH WR": "57.3%", "GIH WR": "54.7%", "ATA": "6.47", "ALSA": "4.8", "IWD": "3.69pp", "zScoreGIH": -0.3, "zScoreOH": 0.569, "zScoreIWD": 0.166}, "Aragorn, Company Leader": {"Name": "Aragorn, Company Leader", "Color": "WG", "Rarity": "rare", "# GIH": 9775, "OH WR": "55.0%", "GIH WR": "55.8%", "ATA": "2.51", "ALSA": "2.4", "IWD": "6.38pp", "zScoreGIH": -0.08, "zScoreOH": 0.211, "zScoreIWD": 0.788}, "Aragorn, the Uniter": {"Name": "Aragorn, the Uniter", "Color": "WURG", "Rarity": "mythic", "# GIH": 4147, "OH WR": "55.5%", "GIH WR": "56.3%", "ATA": "2.68", "ALSA": "2.59", "IWD": "10.17pp", "zScoreGIH": 0.014, "zScoreOH": 0.288, "zScoreIWD": 1.666}, "Arwen, Mortal Queen": {"Name": "Arwen, Mortal Queen", "Color": "WG", "Rarity": "mythic", "# GIH": 6720, "OH WR": "66.0%", "GIH WR": "66.9%", "ATA": "1.81", "ALSA": "1.88", "IWD": "16.48pp", "zScoreGIH": 2.096, "zScoreOH": 1.924, "zScoreIWD": 3.126}, "Arwen Und\u00f3miel": {"Name": "Arwen Und\u00f3miel", "Color": "UG", "Rarity": "uncommon", "# GIH": 16780, "OH WR": "56.2%", "GIH WR": "55.7%", "ATA": "6.64", "ALSA": "4.86", "IWD": "7.56pp", "zScoreGIH": -0.1, "zScoreOH": 0.398, "zScoreIWD": 1.061}, "The Balrog, Durin's Bane": {"Name": "The Balrog, Durin's Bane", "Color": "BR", "Rarity": "rare", "# GIH": 12991, "OH WR": "55.9%", "GIH WR": "59.2%", "ATA": "2.26", "ALSA": "2.18", "IWD": "4.97pp", "zScoreGIH": 0.583, "zScoreOH": 0.351, "zScoreIWD": 0.462}, "Bilbo, Retired Burglar": {"Name": "Bilbo, Retired Burglar", "Color": "UR", "Rarity": "uncommon", "# GIH": 56384, "OH WR": "60.5%", "GIH WR": "60.7%", "ATA": "3.94", "ALSA": "3.64", "IWD": "7.96pp", "zScoreGIH": 0.878, "zScoreOH": 1.067, "zScoreIWD": 1.154}, "Butterbur, Bree Innkeeper": {"Name": "Butterbur, Bree Innkeeper", "Color": "WG", "Rarity": "uncommon", "# GIH": 15711, "OH WR": "49.6%", "GIH WR": "53.9%", "ATA": "7.22", "ALSA": "5.0", "IWD": "2.16pp", "zScoreGIH": -0.45, "zScoreOH": -0.63, "zScoreIWD": -0.18}, "Denethor, Ruling Steward": {"Name": "Denethor, Ruling Steward", "Color": "WB", "Rarity": "uncommon", "# GIH": 39117, "OH WR": "56.9%", "GIH WR": "60.3%", "ATA": "3.92", "ALSA": "3.35", "IWD": "5.73pp", "zScoreGIH": 0.799, "zScoreOH": 0.507, "zScoreIWD": 0.638}, "Doors of Durin": {"Name": "Doors of Durin", "Color": "RG", "Rarity": "rare", "# GIH": 6961, "OH WR": "54.5%", "GIH WR": "56.8%", "ATA": "4.41", "ALSA": "3.62", "IWD": "5.75pp", "zScoreGIH": 0.112, "zScoreOH": 0.133, "zScoreIWD": 0.643}, "Elrond, Master of Healing": {"Name": "Elrond, Master of Healing", "Color": "UG", "Rarity": "rare", "# GIH": 7070, "OH WR": "54.6%", "GIH WR": "54.2%", "ATA": "3.64", "ALSA": "3.23", "IWD": "8.17pp", "zScoreGIH": -0.39, "zScoreOH": 0.148, "zScoreIWD": 1.203}, "\u00c9owyn, Fearless Knight": {"Name": "\u00c9owyn, Fearless Knight", "Color": "WR", "Rarity": "rare", "# GIH": 14598, "OH WR": "60.4%", "GIH WR": "62.8%", "ATA": "2.22", "ALSA": "2.26", "IWD": "9.03pp", "zScoreGIH": 1.291, "zScoreOH": 1.052, "zScoreIWD": 1.402}, "Faramir, Prince of Ithilien": {"Name": "Faramir, Prince of Ithilien", "Color": "WU", "Rarity": "rare", "# GIH": 19449, "OH WR": "66.0%", "GIH WR": "65.2%", "ATA": "1.8", "ALSA": "1.91", "IWD": "16.79pp", "zScoreGIH": 1.762, "zScoreOH": 1.924, "zScoreIWD": 3.198}, "Flame of Anor": {"Name": "Flame of Anor", "Color": "UR", "Rarity": "rare", "# GIH": 18454, "OH WR": "57.7%", "GIH WR": "61.3%", "ATA": "3.2", "ALSA": "3.0", "IWD": "8.71pp", "zScoreGIH": 0.996, "zScoreOH": 0.631, "zScoreIWD": 1.328}, "Friendly Rivalry": {"Name": "Friendly Rivalry", "Color": "RG", "Rarity": "uncommon", "# GIH": 11706, "OH WR": "49.8%", "GIH WR": "56.0%", "ATA": "8.99", "ALSA": "6.19", "IWD": "2.18pp", "zScoreGIH": -0.04, "zScoreOH": -0.59, "zScoreIWD": -0.18}, "Frodo Baggins": {"Name": "Frodo Baggins", "Color": "WG", "Rarity": "uncommon", "# GIH": 30166, "OH WR": "63.1%", "GIH WR": "58.6%", "ATA": "4.54", "ALSA": "3.8", "IWD": "10.09pp", "zScoreGIH": 0.466, "zScoreOH": 1.472, "zScoreIWD": 1.647}, "Galadriel of Lothl\u00f3rien": {"Name": "Galadriel of Lothl\u00f3rien", "Color": "UG", "Rarity": "rare", "# GIH": 7957, "OH WR": "53.8%", "GIH WR": "54.7%", "ATA": "3.8", "ALSA": "3.29", "IWD": "6.14pp", "zScoreGIH": -0.3, "zScoreOH": 0.024, "zScoreIWD": 0.733}, "Gandalf the Grey": {"Name": "Gandalf the Grey", "Color": "UR", "Rarity": "rare", "# GIH": 15493, "OH WR": "51.9%", "GIH WR": "56.8%", "ATA": "2.48", "ALSA": "2.41", "IWD": "4.67pp", "zScoreGIH": 0.112, "zScoreOH": -0.27, "zScoreIWD": 0.393}, "Gandalf's Sanction": {"Name": "Gandalf's Sanction", "Color": "UR", "Rarity": "uncommon", "# GIH": 66525, "OH WR": "52.9%", "GIH WR": "63.5%", "ATA": "4.64", "ALSA": "4.16", "IWD": "7.36pp", "zScoreGIH": 1.428, "zScoreOH": -0.11, "zScoreIWD": 1.015}, "Gimli, Mournful Avenger": {"Name": "Gimli, Mournful Avenger", "Color": "RG", "Rarity": "rare", "# GIH": 3315, "OH WR": "49.2%", "GIH WR": "49.8%", "ATA": "6.8", "ALSA": "4.58", "IWD": "-0.38pp", "zScoreGIH": -1.26, "zScoreOH": -0.69, "zScoreIWD": -0.77}, "Gwaihir the Windlord": {"Name": "Gwaihir the Windlord", "Color": "WU", "Rarity": "uncommon", "# GIH": 10380, "OH WR": "47.2%", "GIH WR": "53.4%", "ATA": "8.86", "ALSA": "5.92", "IWD": "3.88pp", "zScoreGIH": -0.55, "zScoreOH": -1.0, "zScoreIWD": 0.21}, "King of the Oathbreakers": {"Name": "King of the Oathbreakers", "Color": "WB", "Rarity": "rare", "# GIH": 12541, "OH WR": "55.2%", "GIH WR": "57.0%", "ATA": "2.19", "ALSA": "2.19", "IWD": "4.6pp", "zScoreGIH": 0.151, "zScoreOH": 0.242, "zScoreIWD": 0.376}, "Legolas, Counter of Kills": {"Name": "Legolas, Counter of Kills", "Color": "UG", "Rarity": "uncommon", "# GIH": 6460, "OH WR": "44.3%", "GIH WR": "48.5%", "ATA": "9.18", "ALSA": "5.91", "IWD": "0.26pp", "zScoreGIH": -1.51, "zScoreOH": -1.45, "zScoreIWD": -0.62}, "Lotho, Corrupt Shirriff": {"Name": "Lotho, Corrupt Shirriff", "Color": "WB", "Rarity": "rare", "# GIH": 6756, "OH WR": "52.7%", "GIH WR": "53.4%", "ATA": "5.73", "ALSA": "4.17", "IWD": "-0.01pp", "zScoreGIH": -0.55, "zScoreOH": -0.14, "zScoreIWD": -0.69}, "Mauh\u00far, Uruk-hai Captain": {"Name": "Mauh\u00far, Uruk-hai Captain", "Color": "BR", "Rarity": "uncommon", "# GIH": 39968, "OH WR": "62.2%", "GIH WR": "58.1%", "ATA": "4.17", "ALSA": "3.53", "IWD": "3.17pp", "zScoreGIH": 0.367, "zScoreOH": 1.332, "zScoreIWD": 0.045}, "Merry, Esquire of Rohan": {"Name": "Merry, Esquire of Rohan", "Color": "WR", "Rarity": "rare", "# GIH": 7882, "OH WR": "59.9%", "GIH WR": "55.8%", "ATA": "4.6", "ALSA": "3.66", "IWD": "3.83pp", "zScoreGIH": -0.08, "zScoreOH": 0.974, "zScoreIWD": 0.198}, "The Mouth of Sauron": {"Name": "The Mouth of Sauron", "Color": "UB", "Rarity": "uncommon", "# GIH": 51103, "OH WR": "55.7%", "GIH WR": "62.1%", "ATA": "4.01", "ALSA": "3.46", "IWD": "7.91pp", "zScoreGIH": 1.153, "zScoreOH": 0.32, "zScoreIWD": 1.142}, "Old Man Willow": {"Name": "Old Man Willow", "Color": "BG", "Rarity": "uncommon", "# GIH": 34134, "OH WR": "56.5%", "GIH WR": "60.9%", "ATA": "4.45", "ALSA": "3.65", "IWD": "7.72pp", "zScoreGIH": 0.917, "zScoreOH": 0.444, "zScoreIWD": 1.099}, "Pippin, Guard of the Citadel": {"Name": "Pippin, Guard of the Citadel", "Color": "WU", "Rarity": "rare", "# GIH": 10312, "OH WR": "60.6%", "GIH WR": "58.9%", "ATA": "3.39", "ALSA": "3.12", "IWD": "11.29pp", "zScoreGIH": 0.524, "zScoreOH": 1.083, "zScoreIWD": 1.925}, "Prince Imrahil the Fair": {"Name": "Prince Imrahil the Fair", "Color": "WU", "Rarity": "uncommon", "# GIH": 23677, "OH WR": "55.8%", "GIH WR": "57.2%", "ATA": "6.34", "ALSA": "4.8", "IWD": "8.21pp", "zScoreGIH": 0.191, "zScoreOH": 0.335, "zScoreIWD": 1.212}, "Ringsight": {"Name": "Ringsight", "Color": "UB", "Rarity": "uncommon", "# GIH": 9048, "OH WR": "48.9%", "GIH WR": "57.7%", "ATA": "9.86", "ALSA": "6.83", "IWD": "3.54pp", "zScoreGIH": 0.289, "zScoreOH": -0.73, "zScoreIWD": 0.131}, "Rise of the Witch-king": {"Name": "Rise of the Witch-king", "Color": "BG", "Rarity": "uncommon", "# GIH": 22305, "OH WR": "51.7%", "GIH WR": "58.5%", "ATA": "6.53", "ALSA": "4.79", "IWD": "4.13pp", "zScoreGIH": 0.446, "zScoreOH": -0.3, "zScoreIWD": 0.268}, "Samwise Gamgee": {"Name": "Samwise Gamgee", "Color": "WG", "Rarity": "rare", "# GIH": 9311, "OH WR": "57.7%", "GIH WR": "57.8%", "ATA": "3.27", "ALSA": "2.93", "IWD": "6.95pp", "zScoreGIH": 0.308, "zScoreOH": 0.631, "zScoreIWD": 0.92}, "Saruman of Many Colors": {"Name": "Saruman of Many Colors", "Color": "WUB", "Rarity": "mythic", "# GIH": 4072, "OH WR": "46.2%", "GIH WR": "53.7%", "ATA": "2.58", "ALSA": "2.45", "IWD": "4.06pp", "zScoreGIH": -0.49, "zScoreOH": -1.15, "zScoreIWD": 0.251}, "Sauron, the Dark Lord": {"Name": "Sauron, the Dark Lord", "Color": "UBR", "Rarity": "mythic", "# GIH": 8654, "OH WR": "59.4%", "GIH WR": "63.2%", "ATA": "1.44", "ALSA": "1.49", "IWD": "12.78pp", "zScoreGIH": 1.369, "zScoreOH": 0.896, "zScoreIWD": 2.27}, "Sauron's Ransom": {"Name": "Sauron's Ransom", "Color": "UB", "Rarity": "rare", "# GIH": 14258, "OH WR": "56.8%", "GIH WR": "61.6%", "ATA": "4.37", "ALSA": "3.72", "IWD": "7.65pp", "zScoreGIH": 1.055, "zScoreOH": 0.491, "zScoreIWD": 1.082}, "Shadow Summoning": {"Name": "Shadow Summoning", "Color": "WB", "Rarity": "uncommon", "# GIH": 38438, "OH WR": "61.3%", "GIH WR": "60.5%", "ATA": "5.15", "ALSA": "4.31", "IWD": "6.5pp", "zScoreGIH": 0.839, "zScoreOH": 1.192, "zScoreIWD": 0.816}, "Shadowfax, Lord of Horses": {"Name": "Shadowfax, Lord of Horses", "Color": "WR", "Rarity": "uncommon", "# GIH": 24988, "OH WR": "56.7%", "GIH WR": "57.1%", "ATA": "5.87", "ALSA": "4.47", "IWD": "3.22pp", "zScoreGIH": 0.171, "zScoreOH": 0.475, "zScoreIWD": 0.057}, "Shagrat, Loot Bearer": {"Name": "Shagrat, Loot Bearer", "Color": "BR", "Rarity": "rare", "# GIH": 3354, "OH WR": "54.3%", "GIH WR": "54.4%", "ATA": "6.61", "ALSA": "4.48", "IWD": "-1.13pp", "zScoreGIH": -0.35, "zScoreOH": 0.102, "zScoreIWD": -0.94}, "Sharkey, Tyrant of the Shire": {"Name": "Sharkey, Tyrant of the Shire", "Color": "UB", "Rarity": "rare", "# GIH": 196, "OH WR": "38.1%", "GIH WR": "41.4%", "ATA": "9.13", "ALSA": "5.93", "IWD": "-0.66pp", "zScoreGIH": -2.91, "zScoreOH": -2.42, "zScoreIWD": -0.84}, "Shelob, Child of Ungoliant": {"Name": "Shelob, Child of Ungoliant", "Color": "BG", "Rarity": "rare", "# GIH": 12737, "OH WR": "53.5%", "GIH WR": "58.4%", "ATA": "2.04", "ALSA": "2.02", "IWD": "6.41pp", "zScoreGIH": 0.426, "zScoreOH": -0.02, "zScoreIWD": 0.795}, "Sm\u00e9agol, Helpful Guide": {"Name": "Sm\u00e9agol, Helpful Guide", "Color": "BG", "Rarity": "rare", "# GIH": 10407, "OH WR": "53.9%", "GIH WR": "56.6%", "ATA": "2.53", "ALSA": "2.42", "IWD": "5.15pp", "zScoreGIH": 0.073, "zScoreOH": 0.039, "zScoreIWD": 0.504}, "Strider, Ranger of the North": {"Name": "Strider, Ranger of the North", "Color": "RG", "Rarity": "uncommon", "# GIH": 12998, "OH WR": "53.5%", "GIH WR": "54.2%", "ATA": "8.06", "ALSA": "5.51", "IWD": "2.61pp", "zScoreGIH": -0.39, "zScoreOH": -0.02, "zScoreIWD": -0.08}, "Th\u00e9oden, King of Rohan": {"Name": "Th\u00e9oden, King of Rohan", "Color": "WR", "Rarity": "uncommon", "# GIH": 30662, "OH WR": "59.1%", "GIH WR": "58.0%", "ATA": "4.89", "ALSA": "4.06", "IWD": "4.2pp", "zScoreGIH": 0.348, "zScoreOH": 0.849, "zScoreIWD": 0.284}, "Tom Bombadil": {"Name": "Tom Bombadil", "Color": "WUBRG", "Rarity": "mythic", "# GIH": 106, "OH WR": "30.3%", "GIH WR": "50.7%", "ATA": "7.55", "ALSA": "4.97", "IWD": "6.58pp", "zScoreGIH": -1.08, "zScoreOH": -3.63, "zScoreIWD": 0.835}, "Ugl\u00fak of the White Hand": {"Name": "Ugl\u00fak of the White Hand", "Color": "BR", "Rarity": "uncommon", "# GIH": 20107, "OH WR": "53.6%", "GIH WR": "55.0%", "ATA": "6.43", "ALSA": "4.52", "IWD": "-1.08pp", "zScoreGIH": -0.24, "zScoreOH": -0.0, "zScoreIWD": -0.93}, "And\u00faril, Flame of the West": {"Name": "And\u00faril, Flame of the West", "Color": "", "Rarity": "mythic", "# GIH": 10520, "OH WR": "71.1%", "GIH WR": "69.9%", "ATA": "1.06", "ALSA": "1.06", "IWD": "17.83pp", "zScoreGIH": 2.685, "zScoreOH": 2.718, "zScoreIWD": 3.439}, "Barrow-Blade": {"Name": "Barrow-Blade", "Color": "", "Rarity": "uncommon", "# GIH": 6071, "OH WR": "53.3%", "GIH WR": "52.2%", "ATA": "9.97", "ALSA": "6.5", "IWD": "-1.14pp", "zScoreGIH": -0.79, "zScoreOH": -0.05, "zScoreIWD": -0.95}, "Ent-Draught Basin": {"Name": "Ent-Draught Basin", "Color": "", "Rarity": "uncommon", "# GIH": 1429, "OH WR": "43.3%", "GIH WR": "49.6%", "ATA": "11.39", "ALSA": "7.49", "IWD": "-3.82pp", "zScoreGIH": -1.3, "zScoreOH": -1.61, "zScoreIWD": -1.57}, "Glamdring": {"Name": "Glamdring", "Color": "", "Rarity": "mythic", "# GIH": 4116, "OH WR": "47.8%", "GIH WR": "56.2%", "ATA": "2.54", "ALSA": "2.34", "IWD": "1.27pp", "zScoreGIH": -0.0, "zScoreOH": -0.91, "zScoreIWD": -0.39}, "Horn of Gondor": {"Name": "Horn of Gondor", "Color": "", "Rarity": "rare", "# GIH": 21016, "OH WR": "67.3%", "GIH WR": "68.3%", "ATA": "1.24", "ALSA": "1.25", "IWD": "14.42pp", "zScoreGIH": 2.371, "zScoreOH": 2.127, "zScoreIWD": 2.649}, "Horn of the Mark": {"Name": "Horn of the Mark", "Color": "", "Rarity": "rare", "# GIH": 4617, "OH WR": "48.5%", "GIH WR": "52.1%", "ATA": "4.02", "ALSA": "3.26", "IWD": "-1.63pp", "zScoreGIH": -0.81, "zScoreOH": -0.8, "zScoreIWD": -1.06}, "Inherited Envelope": {"Name": "Inherited Envelope", "Color": "", "Rarity": "common", "# GIH": 40994, "OH WR": "52.2%", "GIH WR": "54.7%", "ATA": "9.6", "ALSA": "6.5", "IWD": "3.23pp", "zScoreGIH": -0.3, "zScoreOH": -0.22, "zScoreIWD": 0.059}, "Lembas": {"Name": "Lembas", "Color": "", "Rarity": "common", "# GIH": 44715, "OH WR": "52.7%", "GIH WR": "57.6%", "ATA": "9.87", "ALSA": "6.72", "IWD": "4.18pp", "zScoreGIH": 0.269, "zScoreOH": -0.14, "zScoreIWD": 0.279}, "Mirror of Galadriel": {"Name": "Mirror of Galadriel", "Color": "", "Rarity": "uncommon", "# GIH": 4720, "OH WR": "44.7%", "GIH WR": "51.4%", "ATA": "10.31", "ALSA": "6.68", "IWD": "-0.58pp", "zScoreGIH": -0.94, "zScoreOH": -1.39, "zScoreIWD": -0.82}, "Mithril Coat": {"Name": "Mithril Coat", "Color": "", "Rarity": "rare", "# GIH": 4971, "OH WR": "45.6%", "GIH WR": "47.9%", "ATA": "3.08", "ALSA": "2.63", "IWD": "-3.9pp", "zScoreGIH": -1.63, "zScoreOH": -1.25, "zScoreIWD": -1.59}, "The One Ring": {"Name": "The One Ring", "Color": "", "Rarity": "mythic", "# GIH": 6161, "OH WR": "52.6%", "GIH WR": "58.2%", "ATA": "1.38", "ALSA": "1.4", "IWD": "4.03pp", "zScoreGIH": 0.387, "zScoreOH": -0.16, "zScoreIWD": 0.244}, "Palant\u00edr of Orthanc": {"Name": "Palant\u00edr of Orthanc", "Color": "", "Rarity": "mythic", "# GIH": 10363, "OH WR": "66.9%", "GIH WR": "61.9%", "ATA": "1.29", "ALSA": "1.31", "IWD": "11.04pp", "zScoreGIH": 1.114, "zScoreOH": 2.064, "zScoreIWD": 1.867}, "Phial of Galadriel": {"Name": "Phial of Galadriel", "Color": "", "Rarity": "rare", "# GIH": 14467, "OH WR": "55.2%", "GIH WR": "57.1%", "ATA": "2.24", "ALSA": "2.14", "IWD": "3.52pp", "zScoreGIH": 0.171, "zScoreOH": 0.242, "zScoreIWD": 0.126}, "Shire Scarecrow": {"Name": "Shire Scarecrow", "Color": "", "Rarity": "common", "# GIH": 13044, "OH WR": "47.8%", "GIH WR": "50.8%", "ATA": "11.9", "ALSA": "8.35", "IWD": "0.26pp", "zScoreGIH": -1.06, "zScoreOH": -0.91, "zScoreIWD": -0.62}, "Sting, the Glinting Dagger": {"Name": "Sting, the Glinting Dagger", "Color": "", "Rarity": "rare", "# GIH": 3608, "OH WR": "48.7%", "GIH WR": "50.5%", "ATA": "4.41", "ALSA": "3.3", "IWD": "-1.35pp", "zScoreGIH": -1.12, "zScoreOH": -0.77, "zScoreIWD": -1.0}, "Stone of Erech": {"Name": "Stone of Erech", "Color": "", "Rarity": "uncommon", "# GIH": 409, "OH WR": "41.0%", "GIH WR": "49.1%", "ATA": "11.89", "ALSA": "8.01", "IWD": "-3.51pp", "zScoreGIH": -1.4, "zScoreOH": -1.96, "zScoreIWD": -1.5}, "Wizard's Rockets": {"Name": "Wizard's Rockets", "Color": "", "Rarity": "common", "# GIH": 40170, "OH WR": "53.7%", "GIH WR": "53.6%", "ATA": "10.4", "ALSA": "7.38", "IWD": "1.35pp", "zScoreGIH": -0.51, "zScoreOH": 0.008, "zScoreIWD": -0.37}, "Barad-d\u00fbr": {"Name": "Barad-d\u00fbr", "Color": "", "Rarity": "rare", "# GIH": 12874, "OH WR": "56.3%", "GIH WR": "56.7%", "ATA": "3.35", "ALSA": "2.8", "IWD": "1.25pp", "zScoreGIH": 0.092, "zScoreOH": 0.413, "zScoreIWD": -0.39}, "Great Hall of the Citadel": {"Name": "Great Hall of the Citadel", "Color": "", "Rarity": "common", "# GIH": 78323, "OH WR": "54.9%", "GIH WR": "55.0%", "ATA": "8.04", "ALSA": "5.92", "IWD": "3.33pp", "zScoreGIH": -0.24, "zScoreOH": 0.195, "zScoreIWD": 0.082}, "The Grey Havens": {"Name": "The Grey Havens", "Color": "", "Rarity": "uncommon", "# GIH": 5523, "OH WR": "47.0%", "GIH WR": "53.2%", "ATA": "10.49", "ALSA": "6.73", "IWD": "0.24pp", "zScoreGIH": -0.59, "zScoreOH": -1.03, "zScoreIWD": -0.63}, "Minas Tirith": {"Name": "Minas Tirith", "Color": "", "Rarity": "rare", "# GIH": 10334, "OH WR": "54.2%", "GIH WR": "55.5%", "ATA": "4.0", "ALSA": "3.19", "IWD": "1.49pp", "zScoreGIH": -0.14, "zScoreOH": 0.086, "zScoreIWD": -0.34}, "Mines of Moria": {"Name": "Mines of Moria", "Color": "", "Rarity": "rare", "# GIH": 8378, "OH WR": "56.4%", "GIH WR": "54.3%", "ATA": "6.77", "ALSA": "4.59", "IWD": "0.55pp", "zScoreGIH": -0.37, "zScoreOH": 0.429, "zScoreIWD": -0.56}, "Mount Doom": {"Name": "Mount Doom", "Color": "", "Rarity": "mythic", "# GIH": 2813, "OH WR": "53.0%", "GIH WR": "56.2%", "ATA": "4.81", "ALSA": "3.54", "IWD": "-0.31pp", "zScoreGIH": -0.0, "zScoreOH": -0.1, "zScoreIWD": -0.75}, "Rivendell": {"Name": "Rivendell", "Color": "", "Rarity": "rare", "# GIH": 11594, "OH WR": "54.4%", "GIH WR": "56.3%", "ATA": "4.83", "ALSA": "3.67", "IWD": "4.14pp", "zScoreGIH": 0.014, "zScoreOH": 0.117, "zScoreIWD": 0.27}, "The Shire": {"Name": "The Shire", "Color": "", "Rarity": "rare", "# GIH": 7587, "OH WR": "54.8%", "GIH WR": "55.0%", "ATA": "5.09", "ALSA": "3.76", "IWD": "3.36pp", "zScoreGIH": -0.24, "zScoreOH": 0.179, "zScoreIWD": 0.089}, "Shire Terrace": {"Name": "Shire Terrace", "Color": "", "Rarity": "common", "# GIH": 63428, "OH WR": "52.3%", "GIH WR": "53.7%", "ATA": "8.75", "ALSA": "5.94", "IWD": "0.95pp", "zScoreGIH": -0.49, "zScoreOH": -0.2, "zScoreIWD": -0.46}}, "generalStats": {"OH WR": {"\u03bc": 53.644827586206894, "\u03c3": 6.419709091307549}, "GIH WR": {"\u03bc": 56.227586206896575, "\u03c3": 5.0906124176399095}, "IWD": {"\u03bc": 2.971915708812261, "\u03c3": 4.3203501534984055}}}